octothorpe/__init__.py
octothorpe/ami.py
octothorpe/asyncagi.py
octothorpe/base.py
octothorpe/channel.py
octothorpe/test/__init__.py
octothorpe/test/test_ami.py
octothorpe/test/test_asyncagi.py
octothorpe/test/test_base.py
octothorpe-0.5.dist-info/DESCRIPTION.rst
octothorpe-0.5.dist-info/METADATA
octothorpe-0.5.dist-info/metadata.json
octothorpe-0.5.dist-info/RECORD
octothorpe-0.5.dist-info/top_level.txt
octothorpe-0.5.dist-info/WHEEL
