Metadata-Version: 2.0
Name: octothorpe
Version: 0.5
Summary: Asterisk Manager Interface library for the Twisted engine
Home-page: http://www.zigg.com/code/octothorpe/
Author: Matt Behrens
Author-email: matt@zigg.com
License: UNKNOWN
Platform: UNKNOWN
Classifier: Development Status :: 3 - Alpha
Classifier: Framework :: Twisted
Classifier: License :: OSI Approved :: MIT License
Classifier: Topic :: Communications :: Telephony
Requires: Twisted
Requires-Dist: Twisted
